{
  "irVersion": "10",
  "producerName": "skl2onnx",
  "producerVersion": "1.19.1",
  "domain": "ai.onnx",
  "modelVersion": "0",
  "docString": "",
  "graph": {
    "node": [
      {
        "input": [
          "X"
        ],
        "output": [
          "cast_input"
        ],
        "name": "Cast",
        "opType": "Cast",
        "attribute": [
          {
            "name": "to",
            "i": "11",
            "type": "INT"
          }
        ],
        "domain": ""
      },
      {
        "input": [
          "cast_input",
          "coefficient"
        ],
        "output": [
          "mul_result"
        ],
        "name": "MatMul",
        "opType": "MatMul",
        "domain": ""
      },
      {
        "input": [
          "mul_result",
          "intercepts"
        ],
        "output": [
          "add_result"
        ],
        "name": "Add",
        "opType": "Add",
        "domain": ""
      },
      {
        "input": [
          "add_result"
        ],
        "output": [
          "next_activations"
        ],
        "name": "Relu",
        "opType": "Relu",
        "domain": ""
      },
      {
        "input": [
          "next_activations",
          "coefficient1"
        ],
        "output": [
          "mul_result1"
        ],
        "name": "MatMul1",
        "opType": "MatMul",
        "domain": ""
      },
      {
        "input": [
          "mul_result1",
          "intercepts1"
        ],
        "output": [
          "add_result1"
        ],
        "name": "Add1",
        "opType": "Add",
        "domain": ""
      },
      {
        "input": [
          "add_result1"
        ],
        "output": [
          "next_activations1"
        ],
        "name": "Relu1",
        "opType": "Relu",
        "domain": ""
      },
      {
        "input": [
          "next_activations1",
          "coefficient2"
        ],
        "output": [
          "mul_result2"
        ],
        "name": "MatMul2",
        "opType": "MatMul",
        "domain": ""
      },
      {
        "input": [
          "mul_result2",
          "intercepts2"
        ],
        "output": [
          "add_result2"
        ],
        "name": "Add2",
        "opType": "Add",
        "domain": ""
      },
      {
        "input": [
          "add_result2"
        ],
        "output": [
          "out_activations_result"
        ],
        "name": "Relu2",
        "opType": "Softmax",
        "domain": ""
      },
      {
        "input": [
          "out_activations_result"
        ],
        "output": [
          "argmax_output"
        ],
        "name": "ArgMax",
        "opType": "ArgMax",
        "attribute": [
          {
            "name": "axis",
            "i": "1",
            "type": "INT"
          }
        ],
        "domain": ""
      },
      {
        "input": [
          "out_activations_result"
        ],
        "output": [
          "output_probability"
        ],
        "name": "ZipMap",
        "opType": "ZipMap",
        "attribute": [
          {
            "name": "classlabels_int64s",
            "ints": [
              "0",
              "1",
              "2",
              "3",
              "4"
            ],
            "type": "INTS"
          }
        ],
        "domain": "ai.onnx.ml"
      },
      {
        "input": [
          "classes",
          "argmax_output"
        ],
        "output": [
          "array_feature_extractor_result"
        ],
        "name": "ArrayFeatureExtractor",
        "opType": "ArrayFeatureExtractor",
        "domain": "ai.onnx.ml"
      },
      {
        "input": [
          "array_feature_extractor_result",
          "shape_tensor"
        ],
        "output": [
          "reshaped_result"
        ],
        "name": "Reshape",
        "opType": "Reshape",
        "domain": ""
      },
      {
        "input": [
          "reshaped_result"
        ],
        "output": [
          "label"
        ],
        "name": "Cast1",
        "opType": "Cast",
        "attribute": [
          {
            "name": "to",
            "i": "7",
            "type": "INT"
          }
        ],
        "domain": ""
      },
      {
        "input": [
          "label"
        ],
        "output": [
          "output_label"
        ],
        "name": "Cast2",
        "opType": "Cast",
        "attribute": [
          {
            "name": "to",
            "i": "7",
            "type": "INT"
          }
        ],
        "domain": ""
      }
    ],
    "name": "ONNX(MLPClassifier)",
    "initializer": [
      {
        "dims": [
          "20",
          "50"
        ],
        "dataType": 11,
        "name": "coefficient",
        "doubleData": [
          -0.05589594316914598,
          0.4162930838797089,
          0.19984354291685655,
          0.13006014454372972,
          -0.6045351052317354,
          -0.29387440458309466,
          -1.2499826950390294,
          0.33254204551570254,
          0.41913572422404805,
          0.457240082867332,
          -0.815973127490136,
          0.3061732778431143,
          -0.28309378113921607,
          -0.6332894443385865,
          -0.013238819651619745,
          -0.8076879877659027,
          -0.33294394053565685,
          0.06453140284941895,
          0.032269875596483186,
          -0.22557472986840488,
          0.20836308596621045,
          -0.1454036775763666,
          -0.29481033866361267,
          0.15077368949296513,
          -0.01809571798143389,
          0.1746030996615566,
          -0.6109842056305262,
          -0.053682727594292705,
          0.14270356824447092,
          -0.9445235874790846,
          0.09797564061099821,
          0.08049570049217239,
          -0.46785521654334083,
          0.8274173764504376,
          0.3010496040441245,
          0.03277743127747715,
          0.15103390186561186,
          -0.5194475170068719,
          0.4158861524075312,
          -0.41294449342988765,
          -0.3303032385045039,
          -0.021515438546943415,
          -0.6085360858608787,
          0.3585482622366478,
          -0.45582286934241684,
          -0.0009940585860810651,
          -0.46859280919427193,
          -0.27442203459231723,
          0.18789038379942047,
          -0.5553581180864859,
          0.2763694399244599,
          0.1831178142034561,
          0.3594130148159644,
          0.4216280378389893,
          0.1030291073046387,
          0.35511148707228973,
          -0.398573201175499,
          -0.19227221485168722,
          -0.1228448653323762,
          -0.5318523122102072,
          -0.2941693942634693,
          0.15371149557846553,
          0.28345803108724366,
          -0.024303614378464528,
          -0.045696182504570235,
          0.22530954880713325,
          -0.0576194527153978,
          0.22088688209977264,
          -0.14824777602553035,
          0.804772197618361,
          0.18473452433549936,
          -0.0956082324982083,
          -0.4409125625636766,
          0.08582367045755092,
          0.27958952469091525,
          0.27689590363621136,
          0.31552358103536465,
          -0.22415733856655273,
          -0.006821314922971904,
          -0.3780225934533512,
          0.6236206579944602,
          -0.41231881283495125,
          -0.39690329964164145,
          -0.5163176179588679,
          -0.315518700248659,
          -0.33740687301419103,
          0.1446685289630852,
          -0.24194699279746262,
          1.0433387900605822,
          0.5000650839623961,
          -0.5933690645765729,
          0.049920043762580545,
          -0.11874547081706958,
          -0.06546918797638905,
          0.15615671897065272,
          -0.18868577182529273,
          0.029636616225852463,
          -0.23453713300173476,
          -0.10306337391409248,
          -0.24424306396601012,
          -0.5705503672827976,
          0.007516089129049772,
          -0.11599998428175393,
          0.025878442200931995,
          0.5824949070936251,
          -0.5482747343003492,
          0.010806579951672323,
          0.29933253873764176,
          -0.32384737373235106,
          -0.24965907121287872,
          0.2355961813716045,
          -0.3651541190069994,
          0.008219696756406655,
          0.12309475448263643,
          0.23605890455318038,
          0.5197988806443286,
          0.11490927764489473,
          -0.5467247746091761,
          0.20692540223422182,
          -0.01354158309285537,
          0.5502478903942776,
          0.34975666637431496,
          -0.0975103031415164,
          -1.0326874762233238,
          -0.39338306531048617,
          -0.08199747000510653,
          0.15420991538103312,
          0.8268969899849307,
          -0.6583434460763109,
          0.019019767554969896,
          0.18763660622590736,
          -0.01301322934217707,
          -0.15710172649631507,
          -0.21417722741971534,
          0.054216201874283956,
          -0.1347112405698302,
          -0.06011320701670028,
          0.05034792277345042,
          -0.052925513508312934,
          0.5988757112142543,
          0.865224379932875,
          -0.370539327656639,
          0.28657692421036374,
          -0.24704816959877457,
          -0.10384847632991155,
          -0.7705479179186917,
          0.12222949230138667,
          -0.3738444179070957,
          -0.2486841556166277,
          -0.28185567746811774,
          0.20236906215548572,
          0.688487860519335,
          -0.621138902965198,
          0.028873639488438838,
          0.4577074755241553,
          -0.25747442027927925,
          0.06556839592362049,
          0.2299950966154806,
          -0.38684760602678436,
          0.002208049730069222,
          -0.08765985020298873,
          0.27875982731302024,
          0.306806581599277,
          0.06920079925744158,
          0.14724267228858848,
          0.02648590269357208,
          -0.20338180707637507,
          -0.5290301097080329,
          -0.6031953958960573,
          -0.28162064698835604,
          0.10188012900464744,
          -0.6206107840405122,
          0.2960535670285174,
          -0.20644283180323517,
          -0.5269161551126472,
          -0.44973718264798396,
          0.3032402128237653,
          0.14427532458097103,
          0.4996276133158787,
          -0.1270602638624294,
          -0.16016048622158308,
          -0.8497163076970194,
          0.5442011407288126,
          0.07026239720780388,
          -0.30175119463707134,
          0.33810946188972335,
          0.5329348521394738,
          -0.48973906297710396,
          0.07029187962794509,
          -0.2631863958318466,
          -0.728928298363765,
          0.23207179297102679,
          0.2912590404083749,
          0.02205537996856679,
          -0.18660055234124984,
          -0.23155542433724202,
          -0.17067573481047751,
          0.7194319487067905,
          0.8995265665346563,
          0.6562741653375056,
          0.1476831248215084,
          -0.6097556264623002,
          -0.43582427978024285,
          -0.10432938273292483,
          0.003573889158917676,
          -0.39481184400629293,
          -0.2474946690362658,
          0.384735761231402,
          -0.5765414225654628,
          0.1197051512504776,
          0.10613462656770525,
          0.4287336640068409,
          -1.2156602444141114,
          -0.8194640181085651,
          0.708554717031023,
          -0.5766510646657926,
          -0.09332196681301239,
          0.1532778288253446,
          0.15861973488286082,
          0.4931797773755082,
          0.1576219475062023,
          -0.14923508271458544,
          -0.22471366734683879,
          -0.1335566828562868,
          -0.9568510194212667,
          -0.1716471772449248,
          0.6344954708060385,
          -0.37089223468629295,
          0.3772846418073293,
          0.2749083910066974,
          0.28509970132427453,
          -0.2121476714233853,
          0.19327491689741458,
          -0.18259240684617054,
          0.20562650557737408,
          0.11718611771366895,
          -0.8533712262862767,
          -0.3405502329025135,
          0.5419824777105269,
          0.08473028736735772,
          0.1850376311265656,
          0.46749910963790153,
          0.30172816219011384,
          -0.4101228546075045,
          -0.7767127812155841,
          0.01957978089050361,
          -0.3913572670258182,
          0.4877598790852715,
          0.15230921127906522,
          0.23919749521671863,
          -0.30875637083914065,
          -0.4735218491094386,
          0.518003868988858,
          0.09632646331467475,
          -0.41867548158882223,
          -0.4050758313191622,
          0.23476553964876037,
          0.03398510251787108,
          0.058147828883291904,
          -0.40435792972585083,
          0.35466216434180464,
          0.042432378000330215,
          -0.437881770149739,
          0.0012343876445105794,
          0.3169475191982708,
          0.13094287789658135,
          0.10563691656582502,
          0.053726848508709,
          -0.07534805378499042,
          -0.3633056317065796,
          -0.36645369795686766,
          0.5846783128936472,
          0.43973759963455344,
          0.09130873654440942,
          0.13309407603875764,
          0.09319187988793089,
          0.5734375923721776,
          0.3337268712734415,
          -0.09951819842135233,
          -0.05992243873632235,
          0.37995413932666583,
          0.38265607173103794,
          -0.29875344111327434,
          -0.3021687900702155,
          0.14830231625066098,
          -0.19716505155905997,
          0.05435492584908679,
          -0.1136016372221549,
          -0.15065847338030863,
          0.2294042148378156,
          -0.595208458725361,
          -0.7756338254178439,
          0.09310663321110191,
          -0.4726601577054114,
          -0.7727353320795102,
          -0.008536133906380517,
          0.2289101910167466,
          3.212587363483438e-05,
          0.31010102292093544,
          -0.4232241010985747,
          -0.6390264215013809,
          -0.0620214116451104,
          0.05501312948938388,
          0.2403046197171613,
          0.18937990890445053,
          0.6244834068644971,
          -0.26674154568930847,
          -0.04892856929123317,
          0.3716106120009347,
          -0.34355015523340415,
          -0.548643999821415,
          -0.6649210489867187,
          -0.38345613836760684,
          0.4381714824218682,
          0.25990770177375694,
          0.4634862217653043,
          0.2345157813720125,
          -1.2880211101216263,
          -0.7050843749034992,
          -0.16561162638779567,
          0.04550045574840686,
          -0.011386474178471464,
          0.2933350076558622,
          -0.37729674520283923,
          0.17300542480180667,
          0.3479602971270606,
          -0.2946909682482102,
          0.17558468816625308,
          -0.3348524947610837,
          -0.13704578453859367,
          -0.26607234693989884,
          0.2524020381939187,
          -1.2661013063368178,
          0.0311649958987408,
          -0.6930536631174025,
          -0.06840162825632878,
          0.2606674810128202,
          0.03201253814818073,
          0.05928010520342457,
          -0.37920187876183764,
          -0.29657666489966034,
          0.02230240869731288,
          -0.9750887987939584,
          0.027526897477916343,
          -0.16995326308199663,
          0.12681860458275399,
          0.26713085580389456,
          -1.0104968598023774,
          -0.397991409227209,
          -0.4590373352443679,
          0.04880961639542475,
          0.346306229982055,
          0.47900069416224633,
          -1.1234583331186223,
          -0.5418239552040458,
          -0.14807486302978132,
          -0.2323679790953491,
          -0.22421468009700093,
          0.5444175145877017,
          -0.226903948906612,
          -0.007961248628886471,
          0.07964251681089222,
          0.19965411554791865,
          -0.24974143785567862,
          0.2343409116047449,
          -0.3413015738426699,
          0.3028207582164969,
          0.616166854078332,
          -0.40381154681634074,
          -0.2501026329457572,
          -0.2335889057736909,
          -0.6196789340627396,
          -0.06544319059145054,
          -0.05592107669657223,
          -0.3839496518101265,
          -0.15927843155132543,
          -0.17500892463046633,
          -0.2177340526802663,
          0.23822920424530203,
          -0.2827141925560307,
          -0.056088992340021473,
          0.19199305397197,
          0.5238224498350416,
          -0.14435849219836056,
          0.4554159042113391,
          0.17028297399719583,
          0.13785434918365816,
          -0.6514726521300575,
          0.1312132574592569,
          0.025106829197193797,
          0.5795114669707624,
          0.2565807903892927,
          -0.003981542452912377,
          0.34571571707567694,
          -0.17780771226880573,
          0.3940978705019527,
          0.05267399555564611,
          -0.3568534094790607,
          -0.05987307005124804,
          0.7214596595657325,
          3.971397778869403e-169,
          -1.9794553938680456e-168,
          -5.451602963017205e-212,
          -2.9775812179102616e-179,
          -1.268887586590489e-201,
          3.3854346770800947e-172,
          1.1138635186384802e-207,
          -2.2289454908241878e-158,
          -7.448774239540527e-168,
          -2.342770552776291e-167,
          -4.702776431772758e-200,
          4.740795289820773e-162,
          7.408175429998178e-163,
          2.673639137984605e-210,
          -2.2824938217025534e-205,
          3.66375099588914e-212,
          -1.0351057540508553e-197,
          1.642702371934938e-201,
          9.6448908345482e-202,
          1.0832668973802311e-191,
          -2.773953340104652e-185,
          9.881064624754377e-185,
          -2.1459404215595823e-167,
          1.5783276683224107e-211,
          -3.849527746308051e-163,
          4.773278428538482e-213,
          2.2655565759536134e-211,
          1.8560737327486076e-171,
          2.509739384370441e-205,
          -6.351601060138531e-171,
          -1.1579347405314028e-174,
          5.417389511980178e-189,
          -1.6285027899066592e-206,
          -9.792056671507061e-169,
          -2.6276030915437796e-166,
          -1.6718509287294525e-197,
          6.346010751100168e-165,
          4.264694452405212e-180,
          -2.1201910518804222e-197,
          4.306418470300899e-166,
          -2.1825654648432115e-167,
          -4.535082661312465e-157,
          -3.5182231541665435e-206,
          9.886082651569382e-206,
          8.55031007434259e-182,
          -2.1536892186676088e-162,
          -9.101056146358628e-158,
          1.173018138226059e-190,
          -3.544678079286256e-206,
          -4.19748819642737e-166,
          -8.099642982036885e-187,
          -1.6853090455948811e-211,
          -5.889996723436434e-211,
          -3.7103139894575657e-168,
          2.015025641847565e-170,
          2.7570363396167042e-213,
          4.453910297266989e-157,
          -1.2004701587327638e-216,
          -1.0223134042232777e-162,
          8.369121840850733e-172,
          -2.602616765845672e-171,
          -7.505763960886337e-205,
          -4.1329051822083344e-191,
          4.306397971617832e-211,
          -2.4547815385326806e-160,
          -2.2291279071282617e-207,
          1.2248160967803435e-195,
          2.2593014887257226e-173,
          -1.8453830710556747e-187,
          5.96045453194624e-162,
          8.045188033502544e-157,
          -1.434097153822462e-159,
          6.973628109382741e-162,
          1.17430005280263e-169,
          5.908033001447074e-217,
          -2.953456288939601e-157,
          -4.0858657453861128e-165,
          -6.071094742911235e-212,
          9.32682665049308e-160,
          9.299011222423697e-218,
          -8.212488334977523e-206,
          1.3583764671036682e-198,
          -1.1644317457237566e-213,
          -3.8213760753437146e-206,
          5.132242868400246e-209,
          -4.3410172180506606e-169,
          1.9421856869475035e-161,
          -5.184266628248382e-195,
          2.2166757376593579e-162,
          1.7696136344371995e-170,
          2.1355558560855026e-213,
          1.2209944307270684e-208,
          -8.500601269764786e-196,
          -8.887452187119298e-182,
          1.9704903306368127e-215,
          -2.1095456785056127e-204,
          -1.0959037598964204e-209,
          9.406321951992797e-166,
          1.4197438952944936e-158,
          -2.076715471274198e-157,
          -0.21209406761795777,
          0.4584699274712983,
          -0.17925781336598257,
          0.07989191863322381,
          0.11677297887866794,
          -0.3356970183115413,
          0.09844062194596474,
          0.4984879808406427,
          0.2239272967377174,
          0.0900587171659177,
          0.04373601133087795,
          -0.23313696530625133,
          0.07040288364100145,
          0.12700759535078174,
          -0.44971872247640143,
          -0.09641585647821713,
          -0.5329486742876868,
          -0.14003077673897607,
          0.6041206968252971,
          -0.4593410745826982,
          0.38170194566229937,
          -0.19155646501907025,
          0.5675142617261093,
          0.24405965972397003,
          0.43762770550035357,
          -0.27300114592182234,
          0.23331529850072058,
          0.20686846888952334,
          -0.11331405586629319,
          0.34069623104783914,
          0.4045215468613575,
          0.3193210602573674,
          0.2749957815282933,
          0.08010966087256696,
          0.37426991245301655,
          0.16255872800057056,
          0.1660546755037274,
          -0.5533057453839471,
          -0.15118018932964877,
          -0.02761091014715473,
          0.06890739839829631,
          0.18791132435049074,
          -0.8211808891007101,
          -0.12589938733616732,
          0.08161578607656761,
          0.005869808199226175,
          -0.25642750277111437,
          0.18610509191417485,
          0.3044780285280873,
          0.12992733236463902,
          0.08917757537110299,
          0.38932568941799917,
          -0.120511382005597,
          -0.0518652932169649,
          0.41682818037098646,
          -0.25474814235916754,
          -0.016052926453384887,
          -0.4044135687539794,
          0.2895894567125672,
          0.05728171350688189,
          -0.026505071896844885,
          -0.5649069118252319,
          -0.48652059804594244,
          -0.4163667346921989,
          -0.13860403150307482,
          -0.16016682656523606,
          0.10735167968726927,
          0.24696620332049427,
          0.4177870583803214,
          0.0031693454093883323,
          0.27904902482894745,
          0.526765923618175,
          -0.17970557271631868,
          0.25240803540676093,
          0.30368602030083863,
          0.26663241961584244,
          -0.4520250054058124,
          0.5919738160934916,
          0.35399438130503885,
          -0.12496195220075021,
          -0.17620270976418245,
          0.25865827208855047,
          -0.05611058513302038,
          -0.07625589598397275,
          0.07395195184753135,
          0.20587740583857597,
          0.16348853183179363,
          -0.15659445213079226,
          -0.6050978731287203,
          -0.6361261042792227,
          -0.49560202500959794,
          0.4181255492245477,
          0.047809783590179386,
          -0.024845716197875345,
          0.5367956135818468,
          -0.15080133981649138,
          0.03261308295336718,
          0.3154526905460222,
          -0.1836516054200116,
          -0.03592732149058512,
          -0.39558687599561954,
          -0.06926487414217337,
          0.011379335838794573,
          -0.41434831373152325,
          -0.14863376182837537,
          0.1273875418874816,
          -0.4995825330404606,
          -0.3324954344779858,
          -0.021947639551480637,
          0.09988550610884807,
          -0.4904021439765238,
          0.5883283460375506,
          0.06698567000663788,
          -0.4029997895972071,
          0.154988540703125,
          0.28851722173206973,
          -0.6741098414803947,
          -0.2414753913317551,
          0.22729227533155819,
          -0.1402909891873136,
          -0.3232736874035777,
          -0.4644955626779153,
          0.08581165812510028,
          -0.01243289705148538,
          0.2704460144320936,
          0.27138359389813743,
          -0.33600511154934093,
          0.3959064043807221,
          -0.25921236946534554,
          0.17668046750833835,
          0.08602873495227435,
          0.5323091122980393,
          0.06986846895185182,
          0.14572906804656177,
          -0.385891259896049,
          0.18108401588224815,
          -0.2889878126415555,
          -0.513405580217454,
          0.1557057973113266,
          0.006142565392760623,
          -0.1128720021724673,
          0.06959788138482952,
          -0.3384651027418364,
          -0.20929086355728566,
          -0.3090635621043638,
          0.2097186540384094,
          0.22631990384918715,
          0.352644000740614,
          0.48691269292115413,
          -0.20970970931872226,
          -0.3044656666005273,
          -0.1868242480993197,
          0.2828635890258278,
          0.4824450755087296,
          0.01433387733952659,
          -0.20759957384688082,
          0.06655617295241197,
          0.015640991138547587,
          0.2274092697626226,
          -0.10337434060486801,
          -0.377632513909957,
          0.48149807767233016,
          -0.05072456138771732,
          -0.28467812215995425,
          -0.6362754145047376,
          0.012064006331177407,
          -0.06464212696601915,
          -0.009681488045353221,
          -0.43861678791882747,
          -0.3891951088788606,
          -0.3187426726570705,
          0.18018078245069005,
          -0.5508321580275793,
          0.21905824956794026,
          -0.14606258855135748,
          0.4863624230681303,
          -0.6129689571419831,
          0.22628656848418383,
          0.38920013706919143,
          0.13203462725591555,
          0.22671015877727305,
          0.3470332614440912,
          -0.3408984734299337,
          -0.18523239696661198,
          0.25290978876721876,
          0.20409483379957175,
          0.1285669700066045,
          0.007946739737571597,
          0.22066079857458706,
          -0.47350788936142446,
          -0.21729849996105313,
          -0.012806607108948357,
          0.08252943245965215,
          -0.4991314628478513,
          -0.18505974133992775,
          0.2943155344304004,
          -0.25306182498199015,
          0.19899892974631225,
          0.032611145537508726,
          -0.06826776645396757,
          0.1822643530272462,
          -0.42156975849277273,
          -0.20925597773434818,
          -0.129540662016386,
          -0.5671563646201934,
          0.2642840205851246,
          0.2094461976925835,
          0.2439860753089128,
          -0.11923065581760509,
          0.4520121734188156,
          0.04038995387070012,
          -0.14803159668575971,
          0.13217669432045978,
          -0.3786297778922076,
          -0.43002292319121127,
          0.38865228965417475,
          -0.06403280554279826,
          0.0021037903834626812,
          -0.2199278525639922,
          0.2866683155986065,
          0.20484450600711282,
          -0.010609644880743245,
          -0.39234639566330376,
          -0.23270639208570817,
          0.027793545555590424,
          0.7872292273454256,
          -0.47475749837362724,
          -0.004476224936239046,
          -0.6222777466648783,
          0.049286435742071776,
          -0.2763754283424293,
          -0.2201484325051929,
          0.20346037793781968,
          0.044021560945419536,
          -0.13527804269799107,
          0.5850826415289476,
          -0.0654838822889187,
          0.10618347023809188,
          -0.2580822890404107,
          0.07993372369728208,
          -0.1334585789825363,
          -0.5043956436794665,
          0.5201560131153818,
          0.20767017606101187,
          -0.23366343290403502,
          0.07075528403699076,
          -0.2672132133970393,
          -0.141063685268044,
          0.12387946550871169,
          0.028026899430738994,
          -0.17648444526967086,
          0.3497998617482317,
          0.2568907002467614,
          0.03676450431868118,
          -0.08807504103225708,
          0.1413183358728728,
          0.3283024383771267,
          -0.13644807424251482,
          0.2847719500571215,
          0.12092833187757561,
          -0.3007013046656188,
          0.15842173329871004,
          -0.005726439124437022,
          -0.03388135609163261,
          -0.20760098877903085,
          0.07130937217569693,
          0.3072774559044422,
          0.5934763103330963,
          -0.36549214942945796,
          -0.026839053362587816,
          -0.2802250664521362,
          0.354647261692516,
          -0.299233813976768,
          -0.10417560048589479,
          0.07602954183896159,
          -0.44983793077480644,
          -0.32164277286539694,
          0.26558743619349773,
          0.3226891490175593,
          0.3252003775340341,
          0.12800600116915611,
          0.04558235934100784,
          0.24514145181351327,
          -0.2046341552664952,
          0.0284488115019953,
          0.3432112183846649,
          -0.13024912447678078,
          -0.010523113857634667,
          -0.0559572286507415,
          0.5929204166358492,
          -0.20001824599546733,
          0.1186006217205143,
          0.08086632476676321,
          0.4487101055503865,
          -0.36246116573605475,
          0.6353705902671697,
          0.5054993301765792,
          -0.07595931966219668,
          0.14001249247190306,
          -0.24618397094650352,
          0.3484970091805962,
          -0.44330256191718775,
          0.01614691872176227,
          -0.0036251745786752792,
          0.1582896539768744,
          0.0719405263931766,
          -0.19353929203590983,
          0.4333529728144567,
          -0.032424885341781874,
          -0.32439616090146345,
          0.43746764746073297,
          0.7276681701989013,
          -0.030363347697605226,
          -0.06546852185845958,
          0.2700773360020617,
          0.09201732303381388,
          -0.4232101291702532,
          -0.5287940428894005,
          -0.3971641519413634,
          -0.030672390305591025,
          0.11767261370542322,
          0.14516447047316844,
          -0.11296291113671486,
          -0.00033994884622948586,
          -0.33780066739114833,
          -0.020983236585279532,
          -0.0733086378265065,
          -0.2211034659645239,
          0.3373065188787285,
          -0.15781348165137193,
          -0.10910624898226051,
          0.16466702195097382,
          -0.3346177022529456,
          -0.5859970057018518,
          0.13713051627082093,
          -0.29442740823364466,
          0.35032718646853517,
          -0.7334507064081751,
          0.15701031118636258,
          -0.09356683798138696,
          -0.2563859402090631,
          0.044429233826681576,
          -0.005891034991732794,
          0.3243416300040674,
          -0.1385175877423339,
          -0.030448289141065277,
          -1.466512360548402,
          0.4272213152229086,
          -0.42267398342535145,
          -0.12034851422729444,
          -0.5185721205154731,
          0.12696656134136294,
          -0.14186315274556902,
          0.3126093883798353,
          0.033876086450285836,
          -0.271505983293498,
          -0.19903498640532682,
          0.0990405016019805,
          0.15063011055859418,
          -0.25392902018794905,
          0.3383145294285287,
          -0.045078206784243215,
          0.30812324998802715,
          0.11811629379118073,
          0.2902969802418572,
          0.059474572361884415,
          -1.362926726906404,
          -0.14958638669210347,
          -0.01043884688902751,
          0.2203865882478633,
          -0.08979661743247443,
          -0.8370394096089985,
          -0.12920750937366204,
          -0.13035342620854137,
          -0.36456209560141833,
          -0.2036957278296913,
          0.2554277242612617,
          0.24455947079429657,
          -0.2957998899464339,
          -0.420710790046686,
          -0.18760333721418734,
          0.22695866384164975,
          -0.4626310556555567,
          0.2214733025330911,
          0.389939200881056,
          -0.15981177703544394,
          0.23841303392709437,
          -0.12644314528442038,
          -0.6290263551993883,
          -0.21933446278907745,
          0.24395425922566613,
          0.47095815243397027,
          0.17579413045306666,
          -0.09464006857741876,
          0.4356910474912901,
          -0.8632243395704942,
          -0.42103871027408635,
          0.4670274164885136,
          -1.2273484841856326,
          -0.02249389189881203,
          -0.610503641650803,
          -0.528562267032741,
          -0.2090066815059292,
          0.2825344378293561,
          -0.5244818249240002,
          0.21075828375316558,
          0.6746312711719865,
          -0.48764912982316083,
          -0.038970238827250626,
          0.5279158788580416,
          -0.07820874865997325,
          -0.019634514456675713,
          -0.12329928515558496,
          0.17567281958390213,
          -0.12068551271092216,
          0.034584501368817105,
          0.001900438397407894,
          0.4069949184672645,
          0.18706877890708384,
          -0.08843766864900339,
          0.36007740146578177,
          0.011305579709039415,
          0.44056234472821704,
          0.16779962734441817,
          -0.12584762035994385,
          -0.7322358728517844,
          -0.031632000208078916,
          -0.02788581520361881,
          -0.23741064289595487,
          -0.3003297205517402,
          -0.41017897255066366,
          0.3627995156137182,
          0.3195240872626133,
          -0.13828648477509833,
          -0.1877092759658905,
          -0.9779036375998709,
          -0.7136194009569812,
          0.45436190305703666,
          -0.26451249864618276,
          0.008109606507119288,
          -0.41569143861327607,
          0.5107539345246122,
          0.0713339306406911,
          0.25957436672852,
          -0.4039376167294925,
          -0.7676433099680886,
          -0.4488988135788795,
          0.02621359249699976,
          0.5239483270661534,
          -0.07378844660995762,
          -0.21583540081380423,
          0.03159376826647811,
          -0.4173834813488,
          0.024695769400460067,
          0.1289881447607673,
          -0.17172682823127416,
          -0.10622531688080772,
          -0.34841806925273033,
          -0.4464896730035486,
          -0.2136847864737278,
          -0.18472428514415806,
          0.06719679803949959,
          0.09597600003057934,
          -0.04972101751147668,
          -0.3346936492674832,
          0.18465391546975327,
          0.3425589387959525,
          0.26637722045004175,
          0.004733418550436372,
          -0.347455125146693,
          0.4707754584375806,
          0.46830237322430157,
          -0.010347369914022075,
          -0.17327328705498257,
          -0.8317091983221521,
          -0.5301873393511627,
          0.43368829686194826,
          -0.5065035757727937,
          0.20539545279428617,
          0.19313939056925494,
          -0.24017752733404127,
          -0.10926073094824824,
          -0.16712125685424722,
          -0.7230527304238666,
          0.38481837319104567,
          0.0204743929241974,
          0.508461092499094,
          0.10384810724908916,
          -0.41096785547662057,
          0.7539416097472955,
          0.17628322059120255,
          0.28080247534103653,
          -0.04280189603867417,
          0.3903949948511138,
          0.03758750733674284,
          -0.4281905062239575,
          0.1424536817638923,
          -0.23290348444719172,
          0.6822908784640721,
          -0.03439257411915879
        ]
      },
      {
        "dims": [
          "1",
          "50"
        ],
        "dataType": 11,
        "name": "intercepts",
        "doubleData": [
          -0.544643307159473,
          0.08978863164224497,
          0.20632608039959627,
          0.15665140456956345,
          0.5165068249819642,
          0.33637013618135353,
          0.17306356326850783,
          0.22923876339298543,
          -0.31096943230304447,
          0.030002069152323,
          0.18572950792505397,
          0.4505266989395221,
          0.09285160076590004,
          -0.2216571326223247,
          0.03735880295617964,
          0.38167863281374576,
          -0.3576903145805358,
          0.12560280034218396,
          0.5055890369501927,
          -0.23088045163489715,
          0.3778688019600284,
          -0.015325873806709477,
          0.43806601850942223,
          0.4675930083733497,
          0.23294301682404808,
          -0.1013685072460672,
          0.07060103031772781,
          0.14800026276062328,
          -0.1513039427103678,
          0.2559871824139633,
          -0.48067366651342697,
          -0.198635302948642,
          -0.041458459660584576,
          -0.33187128719291675,
          -0.3148906979323912,
          0.30319060756580934,
          -0.34387575558420697,
          0.2763075403420062,
          -0.490996888483199,
          0.03487005892105028,
          0.1847688663944543,
          0.247472153679901,
          -0.2432373159805436,
          0.16762363091340593,
          -0.10476242806721202,
          0.12755326177034326,
          0.015541478459394638,
          -0.5489675418385298,
          0.41762802386370057,
          -0.319388294908669
        ]
      },
      {
        "dims": [
          "50",
          "25"
        ],
        "dataType": 11,
        "name": "coefficient1",
        "doubleData": [
          0.5985629118980392,
          0.3617083345328511,
          0.6410450708293052,
          0.248914176067846,
          0.8632136584411761,
          -0.1845667089437446,
          0.30447985595530597,
          -0.0022835603906815726,
          0.18902257489580604,
          -0.25302003550966506,
          0.6038303471437942,
          0.7118689172151456,
          -0.05085126154440392,
          -0.306627969759955,
          -0.8671619300416441,
          -0.29988122386497373,
          -0.6972992473028143,
          0.12661663388604927,
          0.010070685906819924,
          -0.09900499075186966,
          0.00017674236060486956,
          0.403302350702296,
          -0.3004600483206766,
          -0.2885699643754537,
          0.022987393893652498,
          0.3631540663979467,
          -0.04231447232937489,
          -0.3575885743397424,
          0.0644601699751531,
          0.36237607557921414,
          0.28883105809345394,
          -0.47331561787946946,
          -0.09331735970952658,
          0.39992626319000746,
          -0.382225563862518,
          0.16539454220219443,
          -0.06649082641683925,
          0.14667724934037896,
          0.3994372902820529,
          -0.12675611486525354,
          0.8241844930029567,
          0.2696096476550597,
          0.3065840918362604,
          0.20533043943484303,
          -0.17780695201004998,
          -0.3132737741580317,
          -0.18857709876225714,
          -0.2499061835480114,
          0.5278613153681938,
          -0.2698823153574664,
          -0.6170823614368877,
          0.3772147397334888,
          0.2718739761589,
          0.12380955671742207,
          0.0926884537733431,
          -0.3535580817943963,
          -0.20759467542277185,
          0.2470791664116797,
          0.26333870534990406,
          0.07354982970326378,
          -0.007938248265556279,
          -0.7595776404101613,
          -0.41991457380818165,
          -0.027654274727864834,
          0.2622273455964099,
          -0.1141108161251734,
          -0.14981686354207427,
          0.25343582144793314,
          -0.32187009001964284,
          -0.6805134621976845,
          0.35773010587911536,
          0.5690463034101536,
          0.10830738501129919,
          0.005087951342223269,
          0.3440880981536041,
          0.2765649021251951,
          -0.6269740735182546,
          0.16401228195501172,
          0.24626830190695723,
          -0.29317660796356215,
          0.008775573591751741,
          0.30247143407798305,
          -0.4927142645544991,
          -0.2170887590318641,
          0.5384003225901481,
          -0.32786588161662733,
          0.7037278594387804,
          0.0004656537005608484,
          -0.09522365656529543,
          -0.025457202778989982,
          0.2286005102245772,
          -0.35773683143577484,
          0.3524466563280527,
          -0.060006222453155,
          -0.10357237165544364,
          0.22134233326370237,
          0.5225329043574941,
          0.03527356289088413,
          -0.17060059606995553,
          0.4727533732295267,
          0.08500931343917943,
          0.18214304957200145,
          0.3253471986135669,
          0.15183922684254264,
          -0.09056804713933961,
          0.04968368713945339,
          -0.5947035522377552,
          0.40958421373168963,
          0.36278925275935353,
          -0.24445424155024537,
          0.5025709791819849,
          -0.30715676746024567,
          -0.24483196754279885,
          0.17434885004748313,
          0.061207058667211926,
          0.4109024068395546,
          -0.12942323260238653,
          0.3144425480340377,
          -0.507680723966608,
          0.24322495815148268,
          0.08436844952639062,
          0.8591971117992544,
          -0.9165787279890597,
          -0.3434641775287023,
          0.38044226130695896,
          -0.0007468910774021583,
          0.222625366910889,
          -0.18952892849954514,
          -0.12767327310171553,
          0.25173856336889944,
          0.31674535721469077,
          -0.12269342063977648,
          -0.09565781953225756,
          0.2107409330109158,
          -1.1390280398256036,
          0.07151709243127674,
          0.2821637557843596,
          -0.6341254533148517,
          -0.18572125092775946,
          -0.21397681534918025,
          -0.48308982861926636,
          0.24935310876527947,
          -0.08166978353148223,
          -0.08654334825042347,
          -0.3744061196555936,
          0.13472401209191046,
          -0.052096060507412625,
          0.5495327688225636,
          0.5986259803979699,
          -0.3027234650063768,
          0.27052610282708506,
          -0.6400893964639545,
          -1.0146663284044044,
          -0.4424876695087773,
          0.21230608683134028,
          0.5117358718987555,
          0.05080513243461758,
          -0.15298711181119543,
          -0.9078515924323017,
          0.4607384660804867,
          -0.26804921923918484,
          0.09351322029216963,
          -0.13834140702398526,
          0.020252117801302004,
          0.10094786783323675,
          -0.1847067991674701,
          -0.48791819293974276,
          0.13843701229322428,
          0.4896140386255968,
          -0.37273025930662357,
          0.3483912166567593,
          0.031826053859256825,
          -0.09274381763431046,
          0.27928008105683044,
          0.09180163606701028,
          0.2471083635837529,
          -0.1856237973512316,
          0.07263532146981269,
          0.61641068815024,
          0.12409627932938913,
          0.31124931912316844,
          -0.26308390355822797,
          -0.36158421977234,
          -0.5765524327338422,
          -0.0032547864159960804,
          -0.3862446848437165,
          0.20499133102385841,
          0.0429127050110442,
          -0.19132548289024545,
          -0.36223048354114373,
          0.4727041748675972,
          0.019547919543000336,
          0.47387939816929237,
          0.21754872852466522,
          0.30037939797643437,
          0.1388116634803029,
          -0.5960929167748771,
          0.15480026196482952,
          0.5893859572611949,
          -0.049141002302792,
          0.253216276840627,
          0.2082526860209922,
          0.08731247517946468,
          -0.613242004119577,
          0.2600131845623453,
          0.19650983860418786,
          0.06702169324257677,
          0.017499505485603393,
          -0.2795254074984017,
          0.35048183514088876,
          -0.10293431791215023,
          0.0899554027353762,
          -0.25291764228754865,
          -0.0747526047414111,
          -0.43561618622390236,
          -0.6225864030542533,
          -0.23891268564571008,
          0.12158500627965041,
          0.35078176708473796,
          -1.5301069648145584,
          0.10344004404006651,
          0.16124987946477626,
          0.12208528820045478,
          -0.23265938829058216,
          -0.017096766311341563,
          -0.26219476291786525,
          -0.04121893477451713,
          0.27951526700209006,
          -0.21941336370822018,
          0.05554225282265876,
          0.31535733918524783,
          0.31525814753153014,
          -0.19971471661216922,
          -0.4877094176829679,
          0.03506271432616019,
          -0.4800335708299616,
          0.24417854396518598,
          0.1555384165785824,
          -0.845004875518522,
          -0.13479587645276558,
          -0.46702305269134686,
          0.11856646958887222,
          0.3687212945984112,
          0.22037610309412206,
          0.06230997637306922,
          -0.314302705427624,
          0.11201787217173695,
          -0.10924416007959245,
          0.47915902620807793,
          -0.009450210149509352,
          -0.49708854522899454,
          0.593811164264341,
          -0.8233372530477542,
          -0.3537949325419915,
          -0.07620776604428091,
          0.08423354822900368,
          0.08250190785591222,
          0.5005503264012121,
          0.25924124777129426,
          0.4009753306846182,
          0.1884729019001073,
          0.0290310005732037,
          0.17382573100725082,
          0.5838619965975208,
          0.0400068348334539,
          0.11148435091911582,
          0.10659398477954367,
          0.16629048990546055,
          -0.5127725168767385,
          -0.2882608027272181,
          -0.6550451860610421,
          0.13602028756392257,
          0.2556465176846327,
          -0.27666886494675713,
          0.4502382472544583,
          0.1615829222309259,
          -1.1053750983495516,
          0.04163449472161102,
          -0.1788505390036089,
          0.2095020700218831,
          0.27222658202719086,
          0.34260067998300797,
          0.015991936868770543,
          0.1445065405932021,
          0.48076630565100426,
          -0.1487239155248551,
          -0.006842745141299692,
          0.2623094786895555,
          -0.6640843943059231,
          -0.5095501413432332,
          -0.4603107718744175,
          0.09345859728084928,
          0.043672199428244046,
          0.198255595826163,
          0.3055449407620992,
          0.1216309218592596,
          0.035951421084721234,
          0.5114300846638309,
          0.45260849709993956,
          -0.31063682716676794,
          0.5655626136629197,
          0.24015901051222913,
          -0.16472485947694127,
          0.5669714922060505,
          -0.09484995454685409,
          0.40668995187363505,
          0.2181902236450615,
          0.011153752502517036,
          -0.047973341202896376,
          -0.4094239911407466,
          0.3272377414500513,
          -0.524299157790197,
          0.09737128724501667,
          -0.059090823501505435,
          0.7134821062890542,
          0.1873939176352039,
          0.31385080112815844,
          0.22271637476981862,
          -0.05838103429892557,
          0.05577717962658164,
          0.22714936136372588,
          -0.2979615794423228,
          0.29620522260661336,
          0.004337606703406557,
          -0.27797137138652794,
          0.497728586700002,
          0.09522098296105953,
          -0.14506324259876885,
          -0.3037092716523449,
          0.32674863302335916,
          0.15157174778811022,
          -0.30603781332719004,
          0.33499554308534624,
          -1.1621625497136625,
          0.22639324723509882,
          -0.8595628864163171,
          0.3062021911103191,
          -0.22852980119143668,
          0.167540894974429,
          -0.24111789961467975,
          -0.4116134191326001,
          -0.18620817474634185,
          -0.26486556564298486,
          -0.6303026904198542,
          -0.24329640825656168,
          -0.31048753725223255,
          -0.2743460615870742,
          0.031002902176895716,
          0.2858397409916273,
          0.2461909760850407,
          0.020365936011124495,
          0.30291152525358833,
          -0.43941038442901675,
          0.2976759830260147,
          -0.0025609353351522036,
          0.3398869605383948,
          0.10311181876199213,
          0.47961744392541567,
          0.16991870670952738,
          0.05315971816696965,
          -0.5037385943444199,
          -0.3937658251714169,
          -0.20000485808426333,
          -1.141423609235527,
          0.4515950599318004,
          0.2991808521255985,
          -0.003577753510248455,
          -0.4267312022212468,
          0.11075014594805797,
          0.5592713722972081,
          -0.3282366784248742,
          0.3002638907832295,
          -0.2839809154779616,
          -0.3875667698797472,
          0.690064532475833,
          0.21780197234455267,
          -0.5110134572160661,
          0.08394014742852828,
          0.00890280327777425,
          0.4901007378093186,
          0.13122116030727313,
          -0.2790419636840527,
          -0.029219768282930814,
          0.12752255893777192,
          -0.30374321898269774,
          -0.5590694698415427,
          0.1628924917399039,
          0.22173365521487612,
          -0.4156404656484906,
          0.01320240057308444,
          0.45560816688686245,
          -0.23989764937506497,
          0.3635742392595787,
          0.17783365627054623,
          0.4301597430010251,
          -0.44781797231762954,
          -0.02960822074285451,
          0.6051977311631149,
          0.6075074174369403,
          0.09680533336253838,
          -0.32537877456787745,
          -0.12651612459408068,
          0.6383954681712236,
          0.549321212903527,
          -0.6939225664143305,
          0.037363459988996005,
          -0.06021784712448762,
          0.1278071845495687,
          -0.16866444070047523,
          0.14138047357308878,
          0.26518927528145475,
          0.2384924830646508,
          -0.9463874626251504,
          0.13656433006949206,
          0.5085863329869438,
          -0.16952430673237845,
          0.23234549901699483,
          -0.3537460853889575,
          -0.45371236394225306,
          0.42789922973904776,
          0.10274058092864656,
          0.4119212893555002,
          0.11862985510906929,
          -0.2094723870952919,
          0.5957222321145466,
          0.5657249659939754,
          0.327179932049218,
          0.4124282301981131,
          0.18855350074679342,
          0.08022142609693353,
          0.1748849355365907,
          -0.2137411295342914,
          -0.24972659738433237,
          0.018062973618259814,
          0.08365414033276382,
          -0.22669513341564254,
          0.16220273847809633,
          -0.9454335453641466,
          0.26002902888543955,
          0.27836046123503827,
          -0.28392072445674477,
          -0.295760394955486,
          -0.2948734951960411,
          -0.7149867662291963,
          0.08413421711109245,
          0.38502573050454325,
          -0.28646736469454925,
          -0.4397293978477784,
          -0.3925304400026577,
          0.15543485016663317,
          0.20884437389715763,
          0.22617532985765862,
          -0.01315510356149312,
          -0.6262808117939167,
          0.38991929106501827,
          -0.023673538220584704,
          -0.0729093922283016,
          0.042530334732322914,
          0.16438889114690364,
          0.46150649132465354,
          0.33486256986624724,
          0.5092702755431572,
          0.5592609811713884,
          -0.005846657492059883,
          -0.21800543201703007,
          -0.5532122936778363,
          0.37607834479059143,
          0.3476963062547296,
          0.09654208335768663,
          0.30600466240569363,
          -0.5950127842910605,
          0.22798418370173626,
          -0.19483183033655094,
          -0.12568479517449432,
          -0.10820297147560015,
          -0.17793961857793028,
          -0.08841976752769126,
          0.49164913425254925,
          -0.06104686000841061,
          -0.11386401446122883,
          -0.12298514871238617,
          0.46110001302728515,
          0.6152246298231913,
          0.21512118539579309,
          0.4354149705188217,
          -0.6561211438448046,
          -0.04940275195242959,
          0.34301166607334177,
          -1.0693881396809881,
          -0.1670755173590462,
          -0.22996561178372732,
          -0.04974670783078657,
          -0.11867892962135003,
          -0.9847274134310683,
          0.3525094675795578,
          -0.07194858690580114,
          0.40313083335942956,
          -0.11129107588542926,
          -0.5278260099944839,
          -0.44090634624148706,
          0.5166054764096442,
          0.20640181428092705,
          0.3997496008833825,
          0.10464929900457726,
          -0.18902263692923646,
          -0.16975317348200256,
          0.23444912773467122,
          0.12240216762167248,
          0.19912562848537574,
          0.6325743879209058,
          -0.45040333460963905,
          -0.19478437857441303,
          -0.07900284664877882,
          -0.16127889008556356,
          0.20821583684072917,
          -0.047670293110287865,
          0.23307057788896016,
          -0.3750877571080705,
          -0.3666899386493158,
          -0.2231951754540368,
          -0.15034248894589008,
          -0.27751938542298255,
          0.23751061750256197,
          0.24556631225855508,
          -0.3340690830000645,
          -0.2283980927432471,
          -1.2827210151977495,
          0.5361710855895521,
          0.048900075726715155,
          0.22141274419641824,
          0.18805947453848068,
          0.45939315036225425,
          0.5021737022355164,
          -0.09547669846510035,
          0.3119069683596515,
          -0.217687997455293,
          0.3348658825368216,
          -0.32475654079790567,
          0.4331807287258436,
          0.47916009234795226,
          -0.13472676585669677,
          0.4921408860020105,
          -0.6207692664033857,
          -1.4821671799014227,
          0.15071065065402434,
          0.7262292850563627,
          0.0385971368495927,
          -0.256987819938638,
          -0.34804675805782426,
          0.06266022760950528,
          -0.04533169974310476,
          -0.14248034031117202,
          -0.28654380078066016,
          -0.42509479725888266,
          -0.16223819340274512,
          0.4447880457708737,
          -0.23517251710732912,
          0.1850452705634928,
          -0.2452335626887059,
          -0.06219372135612184,
          0.10105499623979493,
          0.18671619262991063,
          0.36966590712980923,
          -0.7540331890197923,
          -0.009654311564999862,
          0.21930291382856706,
          0.39223959459265845,
          0.055068294145465435,
          0.2541061548211076,
          0.35088616615852575,
          -0.29258358042211924,
          -0.0387292541010401,
          0.6507363820619981,
          0.49119673486481896,
          -0.21881896944351045,
          0.23015262643206733,
          -0.02407062006618863,
          0.15416976864190002,
          -0.3388647159142171,
          -0.007891085773242856,
          0.1665127426105701,
          0.07321294134786746,
          -0.21528727577790796,
          0.021440026630305264,
          0.2932466531171938,
          -0.3099923006859384,
          -0.062290862588440375,
          -0.48131018835550315,
          0.5228690249234397,
          0.11756195325111232,
          -0.3160388469624451,
          0.1573404413020081,
          0.07539588267557895,
          0.33338521207046784,
          0.046819604802590994,
          0.2084602774990712,
          -0.7348021380798124,
          0.43897337852119794,
          0.0024066586681605975,
          0.16162217788627772,
          -0.38620087462962566,
          -0.31434852331161106,
          -0.2895837315911454,
          0.10785260690572737,
          -0.4113056977467808,
          0.27709517995914196,
          0.04706296055516097,
          -0.3761729073695796,
          -0.0992612279654306,
          -0.4625088860309644,
          0.13564612067861662,
          0.11398010048326239,
          0.5382122426986881,
          -0.1083617009558229,
          0.1513850402276183,
          0.3778739252698426,
          -0.06449762573735653,
          0.4398694679934624,
          -0.3067086383687582,
          1.0537440292533748,
          -0.4314410219646777,
          0.3092580184649609,
          0.17899792110503054,
          0.28825171132964567,
          0.2138291169204806,
          -0.19811060109247935,
          -0.11881078181057753,
          0.2794473873023262,
          -0.04745268921588971,
          -0.21352089358646917,
          -0.3310953142417861,
          0.5691953633945099,
          -0.059354238201548365,
          0.14139003687693624,
          -0.1767492639834616,
          0.4214052532786429,
          0.34643582820843527,
          -0.11060756875567407,
          -0.010188727039272795,
          0.40687742797650056,
          -0.29295060731519573,
          -0.4933120183923732,
          0.36240338600031585,
          -0.24369361576189025,
          0.14101201312451522,
          -0.1799573786736106,
          -0.4190956266269655,
          -0.3283556540360155,
          0.024905591244377655,
          0.5417243408595929,
          0.405304152781761,
          0.3264710303340434,
          -0.855893127670113,
          -0.060927427120412436,
          -0.08539828127028373,
          -0.2280896612602157,
          -0.14906132543021625,
          -0.3309810809578045,
          0.2768128397502752,
          -0.2840810573620288,
          -0.11436522691955239,
          -0.4336539064424292,
          0.4281136510106135,
          -0.6214171616273858,
          -0.32805020974933946,
          0.7130441386009995,
          -0.5365105839676079,
          0.5560706218059897,
          0.43047048728745113,
          -0.10065661742129597,
          -0.37607172223163843,
          -0.1597779299044172,
          -0.27004221555422053,
          0.06680861314085723,
          0.08881329993981785,
          -0.12909917334164925,
          -0.031907656728800284,
          0.6918000651090053,
          0.21422314367164516,
          0.049592760473482385,
          0.4144779781073051,
          0.4556610861633217,
          0.4601976327450133,
          0.050830221060812066,
          0.15040586367874725,
          0.3719797786624181,
          -0.07092022446007458,
          -0.6007746811152642,
          0.03830304760624476,
          0.05306231385279002,
          0.26998071468721396,
          0.2772021413227088,
          -0.23975830802180928,
          -0.3658318038289743,
          0.2149099248113542,
          -0.4124575494348901,
          -0.5556883113202608,
          -0.09619861932937804,
          -0.07322843415554227,
          -0.19313084097806768,
          0.46116102165261763,
          -0.242752065236904,
          -0.9296548214084807,
          -0.6296765354796053,
          0.5310312501660609,
          0.6521538609356111,
          0.23916598969968655,
          0.4522736384743979,
          -0.41279166726607813,
          0.09864073845923417,
          -0.28502644952091893,
          0.11156824392553376,
          -0.8399038358521439,
          -0.9225258769861097,
          0.15332284772567123,
          -0.2908479090968572,
          0.43657452169636235,
          -0.1701630854485736,
          0.30689174159793936,
          -0.6226488539911497,
          -0.20768148007882375,
          0.42119412800764383,
          0.643914833392589,
          0.342964165803884,
          0.23064913851803337,
          -0.3382153301921093,
          0.309340453049186,
          -0.05085284053680174,
          -0.16647974325775877,
          -0.0018802556923612932,
          -0.1800377497390676,
          0.5553062441695197,
          0.31249364421020664,
          0.10655188344917578,
          0.2737032971559371,
          0.4848773929738782,
          0.07954666404295761,
          0.26541444856106267,
          0.24775332727266164,
          0.0051342873744916915,
          -0.08215130321929986,
          -0.23628369347484351,
          0.19018735276363805,
          0.3838991096337353,
          -0.10860911201808816,
          -0.40381586703842515,
          0.6219917542863594,
          -0.06666230800401664,
          -0.25108525808266746,
          -0.31067289957973704,
          0.37121608582521987,
          -0.287485758439345,
          -0.6780038102964209,
          -0.1892971760600141,
          0.03718657098088833,
          0.2386251046724152,
          -0.0925610986640522,
          -0.45875663249860515,
          -0.3606219790717904,
          -0.0034788061274753767,
          0.17164662322993504,
          0.24008455010722057,
          -0.08070763943798893,
          0.06841808965633359,
          -0.6904947174406907,
          0.5215401565745522,
          0.14052164562255662,
          0.32245078993830917,
          0.2151796201244487,
          -0.19179741812999151,
          -0.09305155676003919,
          -0.5529027152459546,
          0.7682913942334112,
          0.7288130003951954,
          -0.6261036532745572,
          -0.026148395190091017,
          -0.00922602925589656,
          0.35349586057346116,
          0.3144160556960886,
          -0.17362110859204388,
          0.26731582536929926,
          0.04597714455921965,
          0.013405460876423705,
          0.20268685048833035,
          0.3050964212212446,
          0.04723120928994549,
          -0.5548240689312942,
          -0.2699576544620882,
          0.5483773009343261,
          -0.0034904312947681235,
          -0.25509970020374545,
          0.40565125072018254,
          0.06526964443358012,
          0.029079131167818215,
          0.12705499144502483,
          -0.17073959487220255,
          -0.166132643388634,
          -0.2542898535460331,
          0.2047647414344941,
          0.09569849734293923,
          0.23785346801400187,
          0.21797394469326017,
          -0.231587323863808,
          0.14222132081465114,
          0.5886846541577986,
          -0.26237488254327884,
          0.1972302602209132,
          -0.4381432487586159,
          0.69947800689784,
          -0.029571540964081554,
          0.30607357150179143,
          0.11338292318801234,
          0.22442789740545407,
          0.20137972789160744,
          0.772659577764279,
          0.2998837895655311,
          -0.026214081942178107,
          -0.35151259211016284,
          0.35735454958001206,
          0.24116043789678082,
          -0.17054126501798406,
          -0.9454504557753454,
          0.29997008601254405,
          0.4834440164504438,
          -0.3214134220759739,
          -0.06972714917975648,
          -0.17513656627660257,
          -0.036993109347709975,
          -0.3446426045958503,
          -0.11643082144046349,
          0.47275494012335184,
          0.21091990312169343,
          0.27950089118258825,
          0.5828725770423482,
          -0.9419420601211347,
          0.25773146512551903,
          -0.2599736870637043,
          -0.07390443419441534,
          0.1699284600706951,
          0.03344240577801032,
          -0.7173047345594664,
          -0.09573828598485247,
          -0.10637993276132617,
          -1.1626884488042568,
          0.7432590221291677,
          0.010670302624726437,
          0.1263325751789388,
          -0.5829543557481329,
          -0.1002975697989984,
          0.3817028109574885,
          0.3368463277854333,
          -0.32946221803400577,
          0.5171519822553187,
          -0.43046495372250765,
          0.6573098305267935,
          -0.11720406900548036,
          -0.20487623988270515,
          -0.2967431752293867,
          -0.7459381244035472,
          -0.4525837370927918,
          -0.6288783368652435,
          0.5409932379045239,
          -0.10106761200929358,
          -0.190155119734243,
          0.06380237196011997,
          0.06796413652944785,
          0.4447973403995708,
          0.4238753242580596,
          0.11631425610881481,
          -0.0360327603958728,
          0.021337333754558256,
          -0.3797854818711386,
          -0.2133879291828339,
          -0.032880434804482966,
          0.35739326839853564,
          -0.38355939644135656,
          0.06045214297844944,
          0.4092320646788702,
          0.2176735136741853,
          -0.3886775271697061,
          -0.049914284009762215,
          0.5860468125833262,
          0.041958562044606594,
          -0.15480913787885586,
          0.08970976204905956,
          0.20558325259101398,
          -0.08765645323708943,
          -0.16964071472371134,
          0.07413219621703494,
          -0.4016854739132512,
          -0.26388835962278023,
          -0.4224133840211363,
          0.30592823006711156,
          0.09104535511891115,
          -0.6233023938116835,
          0.25817081424387994,
          0.5375325718820242,
          -0.45046703699945145,
          -0.16147326216117364,
          0.2594274820657823,
          -0.05907427097521554,
          -0.3886815304863634,
          0.0026681693589582695,
          0.1951452631771617,
          0.5838295514876408,
          0.548006252069755,
          0.07080563345804626,
          0.38406912794148407,
          -0.33034984353849256,
          0.22916092098236962,
          -0.5243776051658466,
          -0.28988985833874603,
          -0.6249219558924453,
          0.0221736100732852,
          0.5934061883662541,
          0.030960548807782744,
          0.05989441385770019,
          -0.3015573851746015,
          -1.0855774910723548,
          0.10526756159426864,
          -0.6297587434406404,
          0.3250760497909243,
          -0.35381935802638775,
          -0.04325049349262317,
          0.10444466154907579,
          -0.016285762671755674,
          -0.4504437912258091,
          -0.1407258250242658,
          0.4609897286171311,
          -0.17073005973519234,
          -0.7274847796844195,
          0.2373470228408401,
          -0.11431620458836916,
          -0.4042189558368056,
          -0.06828954109438312,
          -0.2973010659336961,
          0.24001229998595988,
          -0.29142470917467467,
          0.2428724378630324,
          0.6072315578098496,
          0.2667883097791166,
          0.14749058416682412,
          -0.13828114922874926,
          0.062036376616787556,
          -0.08892475088857832,
          0.26573893154491196,
          0.6944380382266452,
          -0.5616879374754983,
          -0.27235097609737824,
          -0.22784893121474925,
          -0.16959654738469995,
          0.16701665537838817,
          0.3262443179456472,
          -0.2540999135886952,
          -0.5507732863142116,
          0.34999515837985146,
          -0.07034422046848118,
          0.4173574140111191,
          -0.6054581226130178,
          -0.4073110536265441,
          -0.25940704787832836,
          -1.0054318132162208,
          0.5503446702266678,
          -1.0785597207030342,
          0.28859069016724376,
          0.19667884749908854,
          -0.10451772111361592,
          0.31284236992133824,
          -0.22987869648204,
          -0.5537354567674865,
          0.11420646116703696,
          0.2575113670064296,
          0.27171306058598166,
          -0.5727409248217482,
          0.09850462207492858,
          -0.006344136503684162,
          0.21862621483116337,
          -0.00816917067806262,
          -0.4281976053348462,
          0.5402331376285193,
          -0.5876990954831582,
          0.26032336837087905,
          -0.15680814510316107,
          0.4894441162213427,
          0.11500009092193327,
          0.06598177335235338,
          0.10394479891688935,
          -0.04095112341164501,
          -0.22823597468528997,
          -0.4461251643878486,
          0.46741543113898404,
          -0.11765842052317187,
          0.14313861905319042,
          -0.6403586706916397,
          0.046904866340012945,
          0.045613020044381655,
          -0.7607145789538701,
          0.3376361633778589,
          0.3863298873950632,
          -1.0439009554229783,
          0.17516991278941635,
          -0.8691876008781375,
          -0.22273225820128498,
          0.31807633015760917,
          0.5749294500496555,
          0.04062517675092184,
          0.003237499154391257,
          -0.3620092458855342,
          0.2821348555745211,
          -0.03181181927155215,
          0.2840358699774493,
          0.39993857470711214,
          0.6163644138064416,
          -0.3604075512683109,
          -0.31435473056873103,
          -0.020982593619799723,
          -0.04916612720855943,
          -0.11239866204339184,
          -1.8582902966912063,
          0.1465291254490492,
          0.4437252120070462,
          -0.8349798474422896,
          -0.45427300572763746,
          0.3237775486852838,
          -0.0597722669455793,
          0.34007732864945794,
          0.2880734796067622,
          0.17050624944434117,
          0.39510095691245734,
          0.03632215813495971,
          -0.4338374930489453,
          -0.7509785784504385,
          -0.08515761950163261,
          0.5076799909095867,
          -0.15404080019232452,
          0.7537492370887968,
          -0.2718421937436105,
          0.5898503034566681,
          0.21216222179214017,
          -0.13775878698386781,
          0.25360467305485884,
          0.29140909151747013,
          -0.18521597219178723,
          0.11385782212563415,
          -0.33563227999099293,
          0.4349820965708535,
          0.29333959781509156,
          0.41187402819366553,
          0.2754865795003371,
          -0.16933582721157206,
          0.6847588526836714,
          -0.53274018035482,
          0.35616180986440027,
          0.04320367764430017,
          0.1274531517188574,
          -0.2988414809617904,
          0.2681655217199714,
          0.2364941085845174,
          -0.6566343423608523,
          0.6182049194100125,
          -1.2183309631920936,
          -0.06963458465700416,
          -0.4372265232310768,
          -0.10663862649663709,
          0.24665267016667503,
          -0.401208246766794,
          -0.9054821320877762,
          -0.019941451046883732,
          -0.2914849535560747,
          -0.15533300436256994,
          0.5686367347014681,
          0.28159876914588583,
          0.10792242435013875,
          -0.32816669305236196,
          0.6246226785821847,
          -0.0765075963459488,
          0.11855446700717175,
          -0.13554613089879786,
          0.2843728021945409,
          -0.5031858202216847,
          -0.5788506227903919,
          -0.037374680884938165,
          0.46373649636111675,
          0.21968541585164106,
          0.5111653045628597,
          0.7433108779255138,
          -0.5574835782963844,
          0.21841043538756463,
          -0.4836404416088271,
          0.019424000679725873,
          0.1950482291744951,
          0.11255489472674146,
          -0.0731718836952591,
          0.17335691308134796,
          0.08515427973290146,
          0.2554905429424617,
          0.3069311234258543,
          0.08629785930102865,
          0.016750970533906732,
          0.4357516129580096,
          0.0578047894182919,
          -0.5062068313135231,
          -0.06585187958453667,
          0.9511108558065233,
          -0.23737463424296248,
          -0.08932600507579389,
          -0.20483796019383635,
          0.26987311459297825,
          -0.1743933122794948,
          0.13874341739089374,
          0.2964620036553278,
          -0.04536404541810264,
          0.03455248898768825,
          0.46227809657872465,
          0.11819366474275572,
          -0.14177042376954613,
          0.43427056793374225,
          -0.20309516071736375,
          0.2407152037575926,
          -0.421571252327966,
          0.35369496405608963,
          -0.18002919196503858,
          -0.2705867750960825,
          0.28909102991398133,
          -0.2033685657856019,
          0.2970358484082624,
          -0.08408830819824917,
          -0.21172165151565064,
          -0.07806517174207768,
          0.09740027539273421,
          0.12003867733024672,
          -0.19476948302667438,
          -0.21764259772857678,
          -0.06632404537660029,
          -0.3911728034002839,
          0.026446985480175312,
          0.1600363328739189,
          0.33851249428209107,
          0.23408265227345257,
          0.41409039847475626,
          -0.21297936033764595,
          0.6486348314763476,
          0.16278545358972915,
          0.4053345294333758,
          -1.6498628696099762,
          -0.19480226506661702,
          -0.46449562038205827,
          0.3116677097676133,
          0.14711354545264238,
          0.05582387824360732,
          0.23553330052458102,
          -0.837855352775141,
          -0.7988584034297993,
          -0.10481460499578771,
          0.4095813584295279,
          0.24236568404479036,
          -0.1899801076644641,
          0.5424277427560814,
          0.034434165241068425,
          0.29563346936179086,
          -0.14566250934862213,
          0.40269049048367644,
          -0.0589780449391272,
          0.3432911506628508,
          -0.004733436202790947,
          -0.19983094544424843,
          0.6461051387471766,
          -0.28916380417856863,
          0.9803312062729612,
          -0.6702123812597925,
          -0.007924182147622407,
          -0.27155795280723116,
          0.17752853399259078,
          0.41888188676673344,
          -0.4261704919561964,
          -0.08544435321727355,
          -0.8833805400354765,
          0.2546324495731849,
          -0.23051423339313987,
          -0.08529724784040293,
          0.008946455592185659,
          0.10939287797818965,
          0.4233963780243585,
          0.36868702667653586,
          0.39914531695113437,
          0.06418180634919235,
          0.6132414350255511,
          -1.0434818432164354,
          -0.33556949174458783,
          -0.6959848115869962,
          0.3867845226688882,
          -0.08618526788756592,
          -0.03821385198487603,
          0.3879008558858822,
          0.4388496417212775,
          -0.1626708381011063,
          -0.051384540064943765,
          0.4918411835360505,
          -0.05122883682237108,
          0.027064860655789138,
          -0.4070762597031873,
          0.5602435006070756,
          0.18489418140186556,
          0.42839594642140744,
          0.07182089929821556,
          -0.1537971084770595,
          0.14883143127493367,
          0.08132128968951154,
          -0.15707283217656776,
          -0.26906023122353023,
          0.0172331684398003,
          0.01628630831585827,
          0.6178572027554647,
          0.33486414797094954,
          0.31627445455655845,
          0.5339105035977482,
          -0.01733988729058364,
          0.3951778405564275,
          -0.14844966472608387,
          -0.11615405231793793,
          -0.8259027017058915,
          0.13354943068689978,
          0.06177398084693904,
          0.1480896010381746,
          0.4466023557458133,
          -0.14226896115962195,
          -0.04991781839633062,
          -0.35995969225295465,
          0.008870927423753542,
          -0.05836296011168117,
          -0.32938525745252334,
          0.12529230916075781,
          -0.0704107240539585,
          0.10066992309069052,
          0.27453282612430346,
          0.2199341240042766,
          1.0081498565017417,
          -0.5161301619526745,
          -0.348325389654546,
          -0.5930230979347889,
          -0.7548118140419742,
          -0.7745091555281918,
          -0.594197403374496,
          -1.7794427406117996,
          -0.5893321796960798,
          -0.10388231609358671,
          0.09120611905132547,
          -0.04748195925727966,
          -0.5075585388095055,
          -0.10765517980869112
        ]
      },
      {
        "dims": [
          "1",
          "25"
        ],
        "dataType": 11,
        "name": "intercepts1",
        "doubleData": [
          0.2751431229732127,
          0.3110674438887723,
          0.0686722741955882,
          -0.2535928403098928,
          0.3028493412365564,
          0.11105138970213041,
          0.020257252655989728,
          0.2500728184082815,
          -0.13164390611300383,
          0.02259965143072273,
          0.16520861302369597,
          0.2001702742585315,
          0.0794839447105189,
          0.033412013971460916,
          0.2802409046046936,
          -0.2452220039714622,
          -0.15985319600511325,
          -0.1452275280638964,
          0.15169762837027984,
          0.005244581163606872,
          0.4031213538679062,
          0.3873887380050178,
          0.25304496157744294,
          0.04031172108652661,
          0.24344195677635885
        ]
      },
      {
        "dims": [
          "25",
          "5"
        ],
        "dataType": 11,
        "name": "coefficient2",
        "doubleData": [
          0.7009642651905634,
          0.525710964247349,
          -0.9417288969312386,
          0.19946648995126054,
          -1.1203808719521036,
          -4.0341919217669995,
          -1.467860597384102,
          0.6200923340255435,
          1.617372230083609,
          0.7757199417417275,
          0.11075899453419293,
          0.8099033703817773,
          -0.9716221796567642,
          -1.0582918178022676,
          0.09129355079504335,
          0.5558452815970275,
          -0.8748318309207423,
          -1.7836920766346112,
          0.1024901004975879,
          1.02700078026144,
          0.23935990470719962,
          0.35669969310443794,
          0.19199781461623527,
          0.26225296308696894,
          -1.4417598121209152,
          -0.023696920528437596,
          0.855616975826397,
          -0.20043499472964993,
          0.561364366571431,
          -0.21383905094306874,
          -1.0253534119952779,
          0.5560644180158193,
          -0.7566044875943373,
          0.7408312189488938,
          -0.22189887970612227,
          -1.4231280212480761,
          0.30458404386557497,
          -0.3254304437121163,
          0.22033534808766506,
          0.4450867882908319,
          -1.0703867058123777,
          -1.3965379250121264,
          0.8436627663938342,
          0.01710573313105909,
          0.9218036399868322,
          -0.49647128046038347,
          0.8337155828669265,
          -0.24496812952751235,
          -0.3002988983282678,
          0.6073417395074074,
          -0.8478101172730625,
          -0.5150732201538805,
          0.8938271342615828,
          -0.0912400305492919,
          0.6530288354234105,
          0.8155923703127841,
          0.7934055426240816,
          0.5522333124361853,
          -0.9374434148396636,
          -1.0047620127287746,
          0.7258699617391248,
          -2.1995298404675943,
          1.1745974610992376,
          0.05440345193163332,
          0.2868426988204584,
          -0.2917738356813793,
          -2.1069445337648562,
          0.032609751644072996,
          -0.07610772411087517,
          0.8957960065205306,
          -0.3353187738773902,
          -0.5380756672276665,
          -1.2733077122750978,
          0.4241733742131073,
          0.7287749318942874,
          0.4567992266479438,
          -1.481179022354921,
          0.4632888367051438,
          -0.4895072338835498,
          0.5285897848319376,
          0.20532035730488962,
          -0.5441513291284971,
          -1.1501272981041417,
          1.077664449955959,
          -0.20952339790083468,
          0.5967756957024128,
          -0.5628974319971555,
          0.32966684884002845,
          -0.8275851906600656,
          -0.15095353418005508,
          2.642612095459474,
          -1.2039802805293771,
          -1.4739363417954823,
          -1.3092618942199743,
          -0.20412459910710834,
          -0.9859370269565899,
          -1.126673724772599,
          1.5171245462471692,
          0.5659266413695754,
          -0.7565529117707009,
          1.087498061035751,
          -0.6272027349394319,
          0.8162951791787281,
          -1.4087545613407872,
          0.6111802814755928,
          -0.2613428907771225,
          0.5625487014283939,
          1.0795212704284671,
          -2.2621996102656676,
          1.1868979616949207,
          -0.4026196344566883,
          -0.4299297504137688,
          0.314491770505307,
          0.7302072212365248,
          -1.1886878111352046,
          0.36028162176977985,
          -0.26763548100993106,
          0.5089819839758193,
          0.46662360159184463,
          -0.5535168561593325,
          0.07723398793614594,
          -0.10916634648410065,
          -0.8797578702714948,
          -1.0404033060570566,
          0.2787075232154484
        ]
      },
      {
        "dims": [
          "1",
          "5"
        ],
        "dataType": 11,
        "name": "intercepts2",
        "doubleData": [
          -0.2792306828924798,
          0.47330320312134533,
          0.1253053640614333,
          -0.025445913486867717,
          -0.04484412497248964
        ]
      },
      {
        "dims": [
          "5"
        ],
        "dataType": 6,
        "int32Data": [
          0,
          1,
          2,
          3,
          4
        ],
        "name": "classes"
      },
      {
        "dims": [
          "1"
        ],
        "dataType": 7,
        "int64Data": [
          "-1"
        ],
        "name": "shape_tensor"
      }
    ],
    "input": [
      {
        "name": "X",
        "type": {
          "tensorType": {
            "elemType": 11,
            "shape": {
              "dim": [
                {},
                {
                  "dimValue": "20"
                }
              ]
            }
          }
        }
      }
    ],
    "output": [
      {
        "name": "output_label",
        "type": {
          "tensorType": {
            "elemType": 7,
            "shape": {
              "dim": [
                {}
              ]
            }
          }
        }
      },
      {
        "name": "output_probability",
        "type": {
          "sequenceType": {
            "elemType": {
              "mapType": {
                "keyType": 7,
                "valueType": {
                  "tensorType": {
                    "elemType": 11
                  }
                }
              }
            }
          }
        }
      }
    ]
  },
  "opsetImport": [
    {
      "domain": "",
      "version": "21"
    },
    {
      "domain": "ai.onnx.ml",
      "version": "1"
    }
  ]
}